fps_terminals/__init__.py
fps_terminals/main.py
fps_terminals/py.typed
fps_terminals/routes.py
fps_terminals/server.py
fps_terminals/win_server.py
fps_terminals-0.9.5.dist-info/licenses/COPYING.md
fps_terminals-0.9.5.dist-info/WHEEL
fps_terminals-0.9.5.dist-info/entry_points.txt
fps_terminals-0.9.5.dist-info/METADATA
fps_terminals-0.9.5.dist-info/RECORD
